oda/__init__.py
oda/antiraid.py
oda_utils-0.1.0.dist-info/METADATA
oda_utils-0.1.0.dist-info/WHEEL
oda_utils-0.1.0.dist-info/top_level.txt
oda_utils-0.1.0.dist-info/RECORD
