Metadata-Version: 2.4
Name: oda-utils
Version: 0.1.0
Summary: Herramientas inteligentes para bots de Discord: Anti-Raid, Embeds y más.
Author: maestro._.oda
Requires-Python: >=3.8
Requires-Dist: discord.py>=2.3.2
Dynamic: author
Dynamic: requires-dist
Dynamic: requires-python
Dynamic: summary
